pybdsim/Beam.py
pybdsim/Builder.py
pybdsim/Constants.py
pybdsim/Data.py
pybdsim/DataUproot.py
pybdsim/Geant4.py
pybdsim/Gmad.py
pybdsim/Joinhistograms.py
pybdsim/ModelProcessing.py
pybdsim/Optics.py
pybdsim/Options.py
pybdsim/Plot.py
pybdsim/Run.py
pybdsim/Visualisation.py
pybdsim/Writer.py
pybdsim/XSecBias.py
pybdsim/_General.py
pybdsim/__init__.py
pybdsim/_version.py
pybdsim/Compare/_BdsimBdsimComparison.py
pybdsim/Compare/_ElegantBdsimComparison.py
pybdsim/Compare/_Mad8BdsimComparison.py
pybdsim/Compare/_Mad8BdsimComparisonOld.py
pybdsim/Compare/_MadxBdsimComparison.py
pybdsim/Compare/_MadxMadxComparison.py
pybdsim/Compare/_MultipleCodeComparison.py
pybdsim/Compare/_SadComparison.py
pybdsim/Compare/_TransportBdsimComparison.py
pybdsim/Compare/__init__.py
pybdsim/Convert/_BdsimElement2TransferMatrix.py
pybdsim/Convert/_BdsimPrimaries2Inrays.py
pybdsim/Convert/_CPyMad2Gmad.py
pybdsim/Convert/_ElegantParamToStrength.py
pybdsim/Convert/_Mad8Saveline2Gmad.py
pybdsim/Convert/_Mad8Twiss2Gmad.py
pybdsim/Convert/_Mad8Twiss2GmadOld.py
pybdsim/Convert/_MadxTfs2Gmad.py
pybdsim/Convert/_MadxTfs2GmadStrength.py
pybdsim/Convert/_Rebdsim2Numpy.py
pybdsim/Convert/_SadFlat2Gmad.py
pybdsim/Convert/_Transport2Gmad.py
pybdsim/Convert/__init__.py
pybdsim/Convert/collimator_analysis.py
pybdsim/Field/FieldPlotter.py
pybdsim/Field/FieldPlotterVtk.py
pybdsim/Field/_Field.py
pybdsim/Field/__init__.py
pybdsim/Testing/__init__.py
pybdsim/Testing/bdsimMadx.py
pybdsim/Testing/trackingTester.py
pybdsim-3.6.1.dist-info/COPYING.txt
pybdsim-3.6.1.dist-info/LICENSE.txt
pybdsim-3.6.1.dist-info/METADATA
pybdsim-3.6.1.dist-info/WHEEL
pybdsim-3.6.1.dist-info/top_level.txt
pybdsim-3.6.1.dist-info/RECORD
