Metadata-Version: 2.1
Name: pybdsim
Version: 3.6.1
Summary: Python utilities for the Monte Carlo Particle accelerator code BDSIM.
Author-email: "JAI@RHUL" <laurie.nevay@cern.ch>
Maintainer-email: Laurie Nevay <laurie.nevay@cern.ch>
Project-URL: homepage, http://www.pp.rhul.ac.uk/bdsim/pybdsim
Project-URL: documentation, http://www.pp.rhul.ac.uk/bdsim/pybdsim
Project-URL: repository, https://bitbucket.org/jairhul/pybdsim
Classifier: Development Status :: 5 - Production/Stable
Classifier: Intended Audience :: Developers
Classifier: Intended Audience :: Science/Research
Classifier: Operating System :: MacOS
Classifier: Operating System :: POSIX
Classifier: Operating System :: Unix
Classifier: Programming Language :: Python
Classifier: Programming Language :: Python :: 3
Classifier: Programming Language :: Python :: 3 :: Only
Classifier: Topic :: Scientific/Engineering
Classifier: Topic :: Scientific/Engineering :: Physics
Classifier: Topic :: Software Development
Requires-Python: >=3.6
License-File: LICENSE.txt
License-File: COPYING.txt
Requires-Dist: matplotlib >=3.0
Requires-Dist: numpy >=1.14
Requires-Dist: importlib-metadata
Requires-Dist: scipy
Requires-Dist: fortranformat
Requires-Dist: pymadx
Requires-Dist: pytransport
Provides-Extra: all
Requires-Dist: awkward ; extra == 'all'
Requires-Dist: uproot ; extra == 'all'
Requires-Dist: pandas ; extra == 'all'
Requires-Dist: pint ; extra == 'all'
Requires-Dist: boost-histogram ; extra == 'all'
Requires-Dist: cpymad ; extra == 'all'
Requires-Dist: mergedeep ; extra == 'all'
Requires-Dist: pysad ; extra == 'all'
Requires-Dist: pymad8 ; extra == 'all'
Provides-Extra: boost_histogram
Requires-Dist: boost-histogram ; extra == 'boost_histogram'
Provides-Extra: cpymad
Requires-Dist: cpymad ; extra == 'cpymad'
Requires-Dist: mergedeep ; extra == 'cpymad'
Provides-Extra: dev
Requires-Dist: pytest ; extra == 'dev'
Requires-Dist: sphinx ; extra == 'dev'
Requires-Dist: sphinx-rtd-theme ; extra == 'dev'
Provides-Extra: pymad8
Requires-Dist: pymad8 ; extra == 'pymad8'
Provides-Extra: pysad
Requires-Dist: pysad ; extra == 'pysad'
Provides-Extra: uproot
Requires-Dist: awkward ; extra == 'uproot'
Requires-Dist: uproot ; extra == 'uproot'
Requires-Dist: pandas ; extra == 'uproot'
Requires-Dist: pint ; extra == 'uproot'
